---
layout: post
title: "Java基础 系列 泛型"
author: "lichao"
header-img: "img/netty/host.png"
catalog: true
tags:
  - java
---

“泛型” 简单的意思就是泛指的类型（参数化类型）。

## Java泛型类

类结构是面向对象中最基本的元素，如果类需要有很好的扩展性，那么可以将其设置成泛型的。假设需要一个数据的包装类，通过传入不同类型的数据，可以存储相应类型的数据。看看这个简单的泛型类的设计：

```
class DataHolder<T>{
    T item;
    
    public void setData(T t) {
    	this.item=t;
    }
    
    public T getData() {
    	return this.item;
    }
}
```

泛型类定义时只需要在类名后面加上类型参数即可，当然也可以添加多个参数，类似于<K,V>,<T,E,K>等。这样就可以在类里面使用定义的类型参数。

> 泛型类最常用的使用场景就是“元组”的使用。我们知道方法return返回值只能返回单个对象。如果我们定义一个泛型类，定义2个甚至3个类型参数，这样我们return对象的时候，构建这样一个“元组”数据，通过泛型传入多个对象，这样我们就可以一次性方法多个数据了。

## Java泛型方法

泛型方法既可以存在于泛型类中，也可以存在于普通的类中。如果使用泛型方法可以解决问题，那么应该尽量使用泛型方法。下面我们通过例子来看一下泛型方法的使用：

```
//注意这个T是一种全新的类型，可以与泛型类中声明的T不是同一种类型。
public <T> void PrinterInfo(T e) {
    System.out.println(e);
}
//调用方法
DataHolder<String> dataHolder=new DataHolder<>();
dataHolder.PrinterInfo(1);
dataHolder.PrinterInfo("AAAAA");
dataHolder.PrinterInfo(8.88f);
```

泛型方法的几个基本特征：
* public与返回值中间非常重要，可以理解为声明此方法为泛型方法。
* 只有声明了的方法才是泛型方法，泛型类中的使用了泛型的成员方法并不是泛型方法。
* 表明该方法将使用泛型类型T，此时才可以在方法中使用泛型类型T。
* 与泛型类的定义一样，此处T可以随便写为任意标识，常见的如T、E、K、V等形式的参数常用于表示泛型。


## Java泛型接口

Java泛型接口的定义和Java泛型类基本相同，下面是一个例子：

```
//定义一个泛型接口
public interface Generator<T> {
    public T next();
}

```

此处有两点需要注意：

* 泛型接口未传入泛型实参时，与泛型类的定义相同，在声明类的时候，需将泛型的声明也一起加到类中。例子如下：
```
/* 即：class DataHolder implements Generator<T>{
 * 如果不声明泛型，如：class DataHolder implements Generator<T>，编译器会报错："Unknown class"
 */
class FruitGenerator<T> implements Generator<T>{
    @Override
    public T next() {
        return null;
    }
}

```

* 如果泛型接口传入类型参数时，实现该泛型接口的实现类，则所有使用泛型的地方都要替换成传入的实参类型。例子如下：

```
class DataHolder implements Generator<String>{
    @Override
    public String next() {
    	return null;
    }
}
```

从这个例子我们看到，实现类里面的所有T的地方都需要实现为String。



## Java泛型擦除及其相关内容
```
Class<?> class1=new ArrayList<String>().getClass();
Class<?> class2=new ArrayList<Integer>().getClass();
System.out.println(class1);		//class java.util.ArrayList
System.out.println(class2);		//class java.util.ArrayList
System.out.println(class1.equals(class2));	//true
```

class1 和class2 居然是同一个类型 ArrayList，在运行时我们传入的类型变量 String 和 Integer 都被丢掉了。Java 语言泛型在设计的时候为了兼容原来的旧代码，Java 的泛型机制使用了“擦除”机制。我们来看一个更彻底的例子

```
class Table {}
class Room {}
class House<Q> {}
class Particle<POSITION, MOMENTUM> {}
//调用代码及输出
List<Table> tableList = new ArrayList<Table>();
Map<Room, Table> maps = new HashMap<Room, Table>();
House<Room> house = new House<Room>();
Particle<Long, Double> particle = new Particle<Long, Double>();
System.out.println(Arrays.toString(tableList.getClass().getTypeParameters()));
System.out.println(Arrays.toString(maps.getClass().getTypeParameters()));
System.out.println(Arrays.toString(house.getClass().getTypeParameters()));
System.out.println(Arrays.toString(particle.getClass().getTypeParameters()));
/** 
[E]
[K, V]
[Q]
[POSITION, MOMENTUM]
 */

```

上面的代码里，我们想在运行时获取类的类型参数，但是我们看到返回的都是“形参”。在运行期我们是获取不到任何已经声明的类型信息的。

**注意：**

编译器虽然会在编译过程中移除参数的类型信息，但是会保证类或方法内部参数类型的一致性。


泛型参数将会被擦除到它的第一个边界（边界可以有多个，重用 extends 关键字，通过它能给与参数类型添加一个边界）。编译器事实上会把类型参数替换为它的第一个边界的类型。如果没有指明边界，那么类型参数将被擦除到Object。下面的例子中，可以把泛型参数T当作HasF类型来使用。

```
public interface HasF {
    void f();
}

public class Manipulator<T extends HasF> {
    T obj;
    public T getObj() {
        return obj;
    }
    public void setObj(T obj) {
        this.obj = obj;
    }
}

```
extend关键字后后面的类型信息决定了泛型参数能保留的信息。Java类型擦除只会擦除到HasF类型

#### 泛型擦除原理

我们通过例子来看一下，先看一个非泛型的版本：

```
// SimpleHolder.java
public class SimpleHolder {
    private Object obj;
    public Object getObj() {
        return obj;
    }
    public void setObj(Object obj) {
        this.obj = obj;
    }
    public static void main(String[] args) {
        SimpleHolder holder = new SimpleHolder();
        holder.setObj("Item");
        String s = (String) holder.getObj();
    }
}
// SimpleHolder.class
public class SimpleHolder {
  public SimpleHolder();
    Code:
       0: aload_0       
       1: invokespecial #1                  // Method java/lang/Object."<init>":()V
       4: return        

  public java.lang.Object getObj();
    Code:
       0: aload_0       
       1: getfield      #2                  // Field obj:Ljava/lang/Object;
       4: areturn       

  public void setObj(java.lang.Object);
    Code:
       0: aload_0       
       1: aload_1       
       2: putfield      #2                  // Field obj:Ljava/lang/Object;
       5: return        

  public static void main(java.lang.String[]);
    Code:
       0: new           #3                  // class SimpleHolder
       3: dup           
       4: invokespecial #4                  // Method "<init>":()V
       7: astore_1      
       8: aload_1       
       9: ldc           #5                  // String Item
      11: invokevirtual #6                  // Method setObj:(Ljava/lang/Object;)V
      14: aload_1       
      15: invokevirtual #7                  // Method getObj:()Ljava/lang/Object;
      18: checkcast     #8                  // class java/lang/String
      21: astore_2      
      22: return        
}
```

下面我们给出一个泛型的版本，从字节码的角度来看看:

```
//GenericHolder.java
public class GenericHolder<T> {
    T obj;
    public T getObj() {
        return obj;
    }
    public void setObj(T obj) {
        this.obj = obj;
    }
    public static void main(String[] args) {
        GenericHolder<String> holder = new GenericHolder<>();
        holder.setObj("Item");
        String s = holder.getObj();
    }
}

//GenericHolder.class
public class GenericHolder<T> {
  T obj;

  public GenericHolder();
    Code:
       0: aload_0       
       1: invokespecial #1                  // Method java/lang/Object."<init>":()V
       4: return        

  public T getObj();
    Code:
       0: aload_0       
       1: getfield      #2                  // Field obj:Ljava/lang/Object;
       4: areturn       

  public void setObj(T);
    Code:
       0: aload_0       
       1: aload_1       
       2: putfield      #2                  // Field obj:Ljava/lang/Object;
       5: return        

  public static void main(java.lang.String[]);
    Code:
       0: new           #3                  // class GenericHolder
       3: dup           
       4: invokespecial #4                  // Method "<init>":()V
       7: astore_1      
       8: aload_1       
       9: ldc           #5                  // String Item
      11: invokevirtual #6                  // Method setObj:(Ljava/lang/Object;)V
      14: aload_1       
      15: invokevirtual #7                  // Method getObj:()Ljava/lang/Object;
      18: checkcast     #8                  // class java/lang/String
      21: astore_2      
      22: return        
}

```

在编译过程中，类型变量的信息是能拿到的。所以，set方法在编译器可以做类型检查，非法类型不能通过编译。但是对于get方法，由于擦除机制，运行时的实际引用类型为Object类型。为了“还原”返回结果的类型，编译器在get之后添加了类型转换。所以，在GenericHolder.class文件main方法主体第18行有一处类型转换的逻辑。它是编译器自动帮我们加进去的。
所以在泛型类对象读取和写入的位置为我们做了处理，为代码添加约束。

#### Java泛型擦除的缺陷及补救措施

泛型类型不能显式地运用在运行时类型的操作当中，例如：转型、instanceof 和 new。因为在运行时，所有参数的类型信息都丢失了。类似下面的代码都是无法通过编译的：

```
public class Erased<T> {
    private final int SIZE = 100;
    public static void f(Object arg) {
        //编译不通过
        if (arg instanceof T) {
        }
        //编译不通过
        T var = new T();
        //编译不通过
        T[] array = new T[SIZE];
        //编译不通过
        T[] array = (T) new Object[SIZE];
    }
}
```
那我们有什么办法来补救呢？下面介绍几种方法来一一解决上面出现的问题。

###### 类型判断问题

我们可以通过下面的代码来解决泛型的类型信息由于擦除无法进行类型判断的问题：

```
/**
 * 泛型类型判断封装类
 * @param <T>
 */
class GenericType<T>{
    Class<?> classType;
    
    public GenericType(Class<?> type) {
        classType=type;
    }
    
    public boolean isInstance(Object object) {
        return classType.isInstance(object);
    }
}



GenericType<A> genericType=new GenericType<>(A.class);
System.out.println("------------");
System.out.println(genericType.isInstance(new A()));
System.out.println(genericType.isInstance(new B()));

```

我们通过记录类型参数的Class对象，然后通过这个Class对象进行类型判断。




## Java泛型通配符
